archimedes_flow_utils/__init__.py
archimedes_flow_utils/logger.py
archimedes_flow_utils/notifications.py
archimedes_flow_utils/prefect.py
archimedes_flow_utils/storage.py
archimedes_flow_utils-1.1.8.dist-info/METADATA
archimedes_flow_utils-1.1.8.dist-info/WHEEL
archimedes_flow_utils-1.1.8.dist-info/RECORD
